canvas_selector/__init__.py
canvas_selector/_version.py
canvas_selector/canvas_selector.py
canvas_selector/load_config.py
canvas_selector-0.9.dist-info/METADATA
canvas_selector-0.9.dist-info/WHEEL
canvas_selector-0.9.dist-info/top_level.txt
canvas_selector-0.9.dist-info/RECORD
