Metadata-Version: 2.4
Name: canvas_selector
Version: 0.9
Summary: Python package for selecting objects from the canvasapi
Home-page: https://github.com/abrown41/canvas_selector
Author: Andrew Brown
Author-email: andrew.brown@qub.ac.uk
License: BSD (3-clause)
Classifier: Development Status :: 2 - Pre-Alpha
Classifier: Natural Language :: English
Classifier: Programming Language :: Python :: 3
Requires-Python: >=3.7
Requires-Dist: canvasapi
Requires-Dist: tqdm
Requires-Dist: inquirer
Dynamic: author
Dynamic: author-email
Dynamic: classifier
Dynamic: description
Dynamic: home-page
Dynamic: license
Dynamic: requires-dist
Dynamic: requires-python
Dynamic: summary
